{
  "op-intents": [
    {
      "name": "op1",
      "type": "Payment",
      "src": {
        "domain": 7,
        "user_name": "a1"
      },
      "dst": {
        "domain": 8,
        "user_name": "a2"
      },
      "amount": "10",
      "unit": "ether",
      "ratio": "1 ether as 2 XYZ"
    }
  ],
  "accounts": [
    {
      "userName": "a1",
      "domain": 7,
      "address": "d3d091e01502d53e3820aed1e6eff3af2673f346"
    },
    {
      "userName": "a2",
      "domain": 8,
      "address": "0xc157a9260be13546d83bd089450e2cc25b38ae29"
    }
  ]
}